topsis_himanshu_102303244/__init__.py
topsis_himanshu_102303244-0.1.1.dist-info/WHEEL
topsis_himanshu_102303244-0.1.1.dist-info/entry_points.txt
topsis_himanshu_102303244-0.1.1.dist-info/METADATA
topsis_himanshu_102303244-0.1.1.dist-info/RECORD
