Metadata-Version: 2.3
Name: topsis-himanshu-102303244
Version: 0.1.1
Summary: A Python package for Topsis method implementation
Author: Himanshu Sardana
Author-email: Himanshu Sardana <himanshusardana2005@gmail.com>
Requires-Dist: argparse>=1.4.0
Requires-Dist: pandas>=2.3.3
Requires-Dist: pyxlsx>=1.1.3
Requires-Python: >=3.11
